mypackage/__init__.py
mypackage/utils.py
mypackageviraj/__init__.py
mypackageviraj/utils.py
mypackageviraj205/__init__.py
mypackageviraj205/utils.py
mypackageviraj205-0.1.0.dist-info/METADATA
mypackageviraj205-0.1.0.dist-info/WHEEL
mypackageviraj205-0.1.0.dist-info/top_level.txt
mypackageviraj205-0.1.0.dist-info/RECORD
